LICENSE
MANIFEST.in
README.md
requirements-dev.txt
requirements-tests.txt
requirements.txt
setup.cfg
setup.py
cli/__init__.py
cli/config.py
cli/constants.py
cli/entrypoint.py
cli/errors.py
cli/utils.py
cli/account/__init__.py
cli/account/cli.py
cli/account/forms.py
cli/account/help.py
cli/account/interfaces.py
cli/account/service.py
cli/atomic_swap/__init__.py
cli/atomic_swap/cli.py
cli/atomic_swap/forms.py
cli/atomic_swap/help.py
cli/atomic_swap/interfaces.py
cli/atomic_swap/service.py
cli/batch/__init__.py
cli/batch/cli.py
cli/batch/forms.py
cli/batch/help.py
cli/batch/interfaces.py
cli/batch/service.py
cli/block/__init__.py
cli/block/cli.py
cli/block/forms.py
cli/block/help.py
cli/block/interfaces.py
cli/block/service.py
cli/generic/__init__.py
cli/generic/forms/__init__.py
cli/generic/forms/fields.py
cli/generic/forms/forms.py
cli/masternode/__init__.py
cli/masternode/cli.py
cli/masternode/forms.py
cli/masternode/help.py
cli/masternode/interfaces.py
cli/masternode/service.py
cli/node/__init__.py
cli/node/cli.py
cli/node/forms.py
cli/node/interfaces.py
cli/node/service.py
cli/node_account/__init__.py
cli/node_account/cli.py
cli/node_account/forms.py
cli/node_account/help.py
cli/node_account/interfaces.py
cli/node_account/service.py
cli/public_key/__init__.py
cli/public_key/cli.py
cli/public_key/forms.py
cli/public_key/help.py
cli/public_key/interfaces.py
cli/public_key/service.py
cli/receipt/__init__.py
cli/receipt/cli.py
cli/receipt/forms.py
cli/receipt/help.py
cli/receipt/interfaces.py
cli/receipt/service.py
cli/state/__init__.py
cli/state/cli.py
cli/state/forms.py
cli/state/help.py
cli/state/interfaces.py
cli/state/service.py
cli/transaction/__init__.py
cli/transaction/cli.py
cli/transaction/forms.py
cli/transaction/help.py
cli/transaction/interfaces.py
cli/transaction/service.py
remme_core_cli.egg-info/PKG-INFO
remme_core_cli.egg-info/SOURCES.txt
remme_core_cli.egg-info/dependency_links.txt
remme_core_cli.egg-info/entry_points.txt
remme_core_cli.egg-info/requires.txt
remme_core_cli.egg-info/top_level.txt