Metadata-Version: 2.1
Name: remme-core-cli
Version: 0.6.0
Summary: The command-line interface (CLI) that provides a set of commands to interact with Remme-core.
Home-page: https://github.com/Remmeauth/remme-core-cli
Author: Remme
Author-email: developers@remme.io
License: MIT
Platform: UNKNOWN
Classifier: Operating System :: OS Independent
Classifier: Intended Audience :: Developers
Classifier: License :: OSI Approved :: MIT License
Classifier: Programming Language :: Python :: 3.6
Classifier: Programming Language :: Python :: 3.7
